MANIFEST.in
README.rst
setup.py
docs/HISTORY.txt
docs/INSTALL.txt
docs/LICENSE.GPL
docs/LICENSE.txt
src/collective/__init__.py
src/collective.portlet.collectionmultiview.egg-info/PKG-INFO
src/collective.portlet.collectionmultiview.egg-info/SOURCES.txt
src/collective.portlet.collectionmultiview.egg-info/dependency_links.txt
src/collective.portlet.collectionmultiview.egg-info/entry_points.txt
src/collective.portlet.collectionmultiview.egg-info/namespace_packages.txt
src/collective.portlet.collectionmultiview.egg-info/not-zip-safe
src/collective.portlet.collectionmultiview.egg-info/requires.txt
src/collective.portlet.collectionmultiview.egg-info/top_level.txt
src/collective/portlet/__init__.py
src/collective/portlet/collectionmultiview/__init__.py
src/collective/portlet/collectionmultiview/collectionmultiview.py
src/collective/portlet/collectionmultiview/configure.zcml
src/collective/portlet/collectionmultiview/i18n.py
src/collective/portlet/collectionmultiview/interfaces.py
src/collective/portlet/collectionmultiview/rebuild_i18n.sh
src/collective/portlet/collectionmultiview/rendererselectwidget.pt
src/collective/portlet/collectionmultiview/vocabulary.py
src/collective/portlet/collectionmultiview/widget.py
src/collective/portlet/collectionmultiview/locales/collective.portlet.collectionmultiview.pot
src/collective/portlet/collectionmultiview/locales/nl/LC_MESSAGES/collective.portlet.collectionmultiview.po
src/collective/portlet/collectionmultiview/profiles/default/metadata.xml
src/collective/portlet/collectionmultiview/profiles/default/portlets.xml
src/collective/portlet/collectionmultiview/renderers/__init__.py
src/collective/portlet/collectionmultiview/renderers/base.py
src/collective/portlet/collectionmultiview/renderers/blog.py
src/collective/portlet/collectionmultiview/renderers/column.py
src/collective/portlet/collectionmultiview/renderers/configure.zcml
src/collective/portlet/collectionmultiview/renderers/default.py
src/collective/portlet/collectionmultiview/renderers/summary.py
src/collective/portlet/collectionmultiview/renderers/templates/blog.pt
src/collective/portlet/collectionmultiview/renderers/templates/column.pt
src/collective/portlet/collectionmultiview/renderers/templates/default.pt
src/collective/portlet/collectionmultiview/renderers/templates/summary.pt
src/collective/portlet/collectionmultiview/tests/__init__.py
src/collective/portlet/collectionmultiview/tests/base.py
src/collective/portlet/collectionmultiview/tests/test_portlet.py