Metadata-Version: 1.1
Name: collective.portlet.collectionmultiview
Version: 2.2
Summary: A collection portlet product which supports multiple views
Home-page: http://www.inigo-tech.com/
Author: Izhar Firdaus
Author-email: izhar@inigo-tech.com
License: GPLv2+
Keywords: plone portlet inigo collection multi view
Platform: UNKNOWN
Classifier: Framework :: Plone
Classifier: Programming Language :: Python
Classifier: Topic :: Software Development :: Libraries :: Python Modules
